flake8_return/__init__.py
flake8_return/errors.py
flake8_return/plugin.py
flake8_return/utils.py
flake8_return/visitors.py
flake8_return-1.1.1.dist-info/entry_points.txt
flake8_return-1.1.1.dist-info/LICENSE
flake8_return-1.1.1.dist-info/WHEEL
flake8_return-1.1.1.dist-info/METADATA
flake8_return-1.1.1.dist-info/RECORD
